sphinx_versioning/__init__.py
sphinx_versioning/sphinx_versioning.py
sphinx_versioning-0.1.5.data/scripts/sphinx-version
sphinx_versioning-0.1.5.dist-info/LICENSE
sphinx_versioning-0.1.5.dist-info/METADATA
sphinx_versioning-0.1.5.dist-info/WHEEL
sphinx_versioning-0.1.5.dist-info/top_level.txt
sphinx_versioning-0.1.5.dist-info/RECORD
