Metadata-Version: 2.1
Name: sphinx-versioning
Version: 0.1.5
Summary: A Sphinx extension to manage versioned documentation
Home-page: https://github.com/Yihengxiong6/sphinx_versioning
Author: Yiheng Xiong
Author-email: georgex8866@gmail.com
License: MIT
Keywords: sphinx documentation versioning
Classifier: Development Status :: 3 - Alpha
Classifier: License :: OSI Approved :: MIT License
Classifier: Programming Language :: Python :: 3
Classifier: Programming Language :: Python :: 3.7
Classifier: Programming Language :: Python :: 3.8
Classifier: Programming Language :: Python :: 3.9
Classifier: Programming Language :: Python :: 3.10
Classifier: Topic :: Documentation
Classifier: Framework :: Sphinx :: Extension
Requires-Python: >=3.7
License-File: LICENSE
Requires-Dist: Sphinx
Requires-Dist: beautifulsoup4
